loclean/resources/__init__.py
loclean/resources/grammars/__init__.py
loclean/resources/grammars/email.gbnf
loclean/resources/grammars/json.gbnf
loclean/resources/grammars/json_generic.gbnf
loclean/resources/grammars/list_str.gbnf
loclean/resources/templates/__init__.py
loclean/resources/templates/cleaning_instruction.j2
loclean/resources/templates/llama_format.j2
loclean/resources/templates/phi3_format.j2
loclean/resources/templates/qwen_format.j2
loclean-0.1.1.dist-info/METADATA
loclean-0.1.1.dist-info/WHEEL
loclean-0.1.1.dist-info/licenses/LICENSE
loclean-0.1.1.dist-info/RECORD
