Metadata-Version: 2.4
Name: loclean
Version: 0.1.1
Summary: High-performance, local-first semantic data cleaning library
Project-URL: Homepage, https://github.com/nxank4/loclean
Project-URL: Repository, https://github.com/nxank4/loclean
Project-URL: Issues, https://github.com/nxank4/loclean/issues
Author: Loclean Contributors
License: Apache-2.0
License-File: LICENSE
Keywords: data-cleaning,data-engineering,etl,llm,local-ai,narwhals,semantic
Classifier: Development Status :: 3 - Alpha
Classifier: Intended Audience :: Developers
Classifier: Intended Audience :: Science/Research
Classifier: License :: OSI Approved :: Apache Software License
Classifier: Programming Language :: Python :: 3.10
Classifier: Programming Language :: Python :: 3.11
Classifier: Programming Language :: Python :: 3.12
Classifier: Topic :: Scientific/Engineering :: Artificial Intelligence
Classifier: Topic :: Software Development :: Libraries :: Python Modules
Requires-Python: >=3.10
Requires-Dist: huggingface-hub>=0.20.0
Requires-Dist: jinja2>=3.0.0
Requires-Dist: llama-cpp-python>=0.2.23
Requires-Dist: narwhals>=2.14.0
Requires-Dist: pydantic>=2.12.5
Requires-Dist: tqdm>=4.66.0
Provides-Extra: all
Requires-Dist: anthropic>=0.18.0; extra == 'all'
Requires-Dist: google-generativeai>=0.3.0; extra == 'all'
Requires-Dist: instructor>=1.0.0; extra == 'all'
Requires-Dist: openai>=1.0.0; extra == 'all'
Requires-Dist: pandas>=2.3.3; extra == 'all'
Requires-Dist: polars>=0.20.0; extra == 'all'
Requires-Dist: pyarrow>=22.0.0; extra == 'all'
Provides-Extra: cloud
Requires-Dist: anthropic>=0.18.0; extra == 'cloud'
Requires-Dist: google-generativeai>=0.3.0; extra == 'cloud'
Requires-Dist: instructor>=1.0.0; extra == 'cloud'
Requires-Dist: openai>=1.0.0; extra == 'cloud'
Provides-Extra: data
Requires-Dist: pandas>=2.3.3; extra == 'data'
Requires-Dist: polars>=0.20.0; extra == 'data'
Requires-Dist: pyarrow>=22.0.0; extra == 'data'
